PyCrosstalk/__init__.py
PyCrosstalk/mom_2d_capacitance.py
PyCrosstalk/process_blockpad.py
PyCrosstalk-0.0.1.dist-info/LICENSE
PyCrosstalk-0.0.1.dist-info/METADATA
PyCrosstalk-0.0.1.dist-info/WHEEL
PyCrosstalk-0.0.1.dist-info/top_level.txt
PyCrosstalk-0.0.1.dist-info/RECORD
