Metadata-Version: 2.1
Name: PyCrosstalk
Version: 0.0.1
Summary: A cable coupling and crosstalk tool
Home-page: https://github.com/rccarroll654/PyCoupling
Author: Russell Carroll
Author-email: russell_carroll@carrelec.com
Project-URL: Bug Tracker, https://github.com/rccarroll654/PyCoupling
Requires-Python: >=3.7
License-File: LICENSE
